environize/__init__.py
environize/decorators.py
environize/loaddata.py
environize/settings.py
environize-0.0.1.dist-info/METADATA
environize-0.0.1.dist-info/RECORD
environize-0.0.1.dist-info/WHEEL
environize-0.0.1.dist-info/top_level.txt
tests/__init__.py
tests/test_decorators.py
tests/test_loaddata.py
tests/project/__init__.py
tests/project/settings.py
tests/project/wsgi.py
tests/project/app/__init__.py
tests/project/app/apps.py
tests/project/app/models.py
tests/project/app/migrations/0001_initial.py
tests/project/app/migrations/0002_auto_20180916_1122.py
tests/project/app/migrations/0003_auto_20180916_1122.py
tests/project/app/migrations/0004_auto_20180917_1538.py
tests/project/app/migrations/__init__.py
