Metadata-Version: 2.1
Name: environize
Version: 0.0.1
Summary: enables environment and state savvy DataMigration tools for Django
Home-page: https://github.com/cgdeboer/environize
Author: Calvin DeBoer
Author-email: cgdeboer@gmail.com
License: UNKNOWN
Platform: UNKNOWN
Classifier: Programming Language :: Python :: 3
Classifier: Programming Language :: Python :: 2
Classifier: License :: OSI Approved :: MIT License
Classifier: Operating System :: OS Independent
